odoo/addons/web_widget_one2many_product_picker_sale_secondary_unit/README.rst
odoo/addons/web_widget_one2many_product_picker_sale_secondary_unit/__init__.py
odoo/addons/web_widget_one2many_product_picker_sale_secondary_unit/__manifest__.py
odoo/addons/web_widget_one2many_product_picker_sale_secondary_unit/i18n/web_widget_one2many_product_picker_sale_secondary_unit.pot
odoo/addons/web_widget_one2many_product_picker_sale_secondary_unit/models/__init__.py
odoo/addons/web_widget_one2many_product_picker_sale_secondary_unit/models/sale_order_line.py
odoo/addons/web_widget_one2many_product_picker_sale_secondary_unit/readme/CONTRIBUTORS.rst
odoo/addons/web_widget_one2many_product_picker_sale_secondary_unit/readme/DESCRIPTION.rst
odoo/addons/web_widget_one2many_product_picker_sale_secondary_unit/static/description/icon.png
odoo/addons/web_widget_one2many_product_picker_sale_secondary_unit/static/description/index.html
odoo/addons/web_widget_one2many_product_picker_sale_secondary_unit/static/src/js/views/abstract_view.js
odoo/addons/web_widget_one2many_product_picker_sale_secondary_unit/static/src/js/views/One2ManyProductPicker/record.js
odoo/addons/web_widget_one2many_product_picker_sale_secondary_unit/static/src/js/views/One2ManyProductPicker/renderer.js
odoo/addons/web_widget_one2many_product_picker_sale_secondary_unit/static/src/js/widgets/field_one2many_product_picker.js
odoo/addons/web_widget_one2many_product_picker_sale_secondary_unit/static/src/scss/_variables.scss
odoo/addons/web_widget_one2many_product_picker_sale_secondary_unit/static/src/xml/one2many_product_picker.xml
odoo/addons/web_widget_one2many_product_picker_sale_secondary_unit/templates/assets.xml
odoo13_addon_web_widget_one2many_product_picker_sale_secondary_unit-13.0.1.0.1.dev7.dist-info/METADATA
odoo13_addon_web_widget_one2many_product_picker_sale_secondary_unit-13.0.1.0.1.dev7.dist-info/WHEEL
odoo13_addon_web_widget_one2many_product_picker_sale_secondary_unit-13.0.1.0.1.dev7.dist-info/top_level.txt
odoo13_addon_web_widget_one2many_product_picker_sale_secondary_unit-13.0.1.0.1.dev7.dist-info/RECORD
