Metadata-Version: 2.1
Name: odoo13-addon-web-widget-one2many-product-picker-sale-secondary-unit
Version: 13.0.1.0.1.dev7
Summary: Adds support for sale secondary unit in the one2many product picker widget
Home-page: https://github.com/OCA/web
Author: Tecnativa, Odoo Community Association (OCA)
Author-email: support@odoo-community.org
License: AGPL-3
Platform: UNKNOWN
Classifier: Programming Language :: Python
Classifier: Framework :: Odoo
Classifier: Framework :: Odoo :: 13.0
Classifier: License :: OSI Approved :: GNU Affero General Public License v3
Requires-Python: >=3.5
Requires-Dist: odoo13-addon-sale-order-secondary-unit
Requires-Dist: odoo13-addon-web-widget-one2many-product-picker
Requires-Dist: odoo <13.1dev,>=13.0a
